async_tasks/__init__.py
async_tasks/executor.py
async_tasks/thread.py
async_tasks/typing.py
async_tasks_python-1.0.0.dist-info/LICENSE
async_tasks_python-1.0.0.dist-info/METADATA
async_tasks_python-1.0.0.dist-info/WHEEL
async_tasks_python-1.0.0.dist-info/RECORD
