Metadata-Version: 2.1
Name: async-tasks-python
Version: 1.0.0
Summary: Async tasks made simple—multi-threaded, stoppable, and timeout-ready.
Home-page: https://del.wang
License: MIT
Keywords: async,tasks,threading,stoppable
Author: Del Wang
Author-email: hello@xbox.work
Maintainer: Del Wang
Maintainer-email: hello@xbox.work
Requires-Python: >=3.8,<4.0
Classifier: License :: OSI Approved :: MIT License
Classifier: Programming Language :: Python :: 3
Classifier: Programming Language :: Python :: 3.8
Classifier: Programming Language :: Python :: 3.9
Classifier: Programming Language :: Python :: 3.10
Classifier: Programming Language :: Python :: 3.11
Classifier: Programming Language :: Python :: 3.12
Classifier: Programming Language :: Python :: 3.13
Project-URL: Changelog, https://github.com/idootop/async-tasks/blob/main/CHANGELOG.md
Project-URL: Documentation, https://github.com/idootop/async-tasks/README.md
Project-URL: Repository, https://github.com/idootop/async-tasks
